pypblib/pblib.cpython-36m-i386-linux-gnu.so
pypblib/__init__.py
pypblib-0.0.4.dist-info/METADATA
pypblib-0.0.4.dist-info/WHEEL
pypblib-0.0.4.dist-info/top_level.txt
pypblib-0.0.4.dist-info/RECORD
pypblib-0.0.4.dist-info/LICENSE.txt
pypblib-0.0.4.dist-info/zip-safe
