Metadata-Version: 1.1
Name: pypblib
Version: 0.0.4
Summary: UNKNOWN
Home-page: https://arcadia.hardlog.udl.cat/hlog-tools/pypblib
Author: Carlos Ansótegui, Toni Pacheco, Josep Pon
Author-email: UNKNOWN
License: UNKNOWN
Keywords: PBLib Pseudo-Boolean CNF PB
Platform: Linux
Classifier: Development Status :: 3 - Alpha
Classifier: Intended Audience :: Developers
Classifier: Intended Audience :: Science/Research
Classifier: Natural Language :: English
Classifier: Programming Language :: Python :: 3
Classifier: Programming Language :: Python :: 2
Classifier: Operating System :: OS Independent
Classifier: Topic :: Scientific/Engineering
Classifier: Topic :: Scientific/Engineering :: Artificial Intelligence
